test/__init__.py
test/conftest.py
test/test_util.py
test/models/__init__.py
test/models/test_bus.py
test/models/test_rail.py
wmataio/__init__.py
wmataio/client.py
wmataio/const.py
wmataio/exceptions.py
wmataio/util.py
wmataio/bus/__init__.py
wmataio/bus/const.py
wmataio/bus/util.py
wmataio/bus/models/__init__.py
wmataio/bus/models/bus_incident.py
wmataio/bus/models/live_position.py
wmataio/bus/models/next_bus.py
wmataio/bus/models/route.py
wmataio/bus/models/route_path.py
wmataio/bus/models/route_schedule.py
wmataio/bus/models/stop.py
wmataio/bus/models/stop_schedule.py
wmataio/models/__init__.py
wmataio/models/area.py
wmataio/models/coordinates.py
wmataio/rail/__init__.py
wmataio/rail/const.py
wmataio/rail/models/__init__.py
wmataio/rail/models/address.py
wmataio/rail/models/elevator_and_escalator_incident.py
wmataio/rail/models/line.py
wmataio/rail/models/live_position.py
wmataio/rail/models/next_train.py
wmataio/rail/models/rail_incident.py
wmataio/rail/models/standard_route.py
wmataio/rail/models/station.py
wmataio/rail/models/station_entrance.py
wmataio/rail/models/station_parking.py
wmataio/rail/models/station_timings.py
wmataio/rail/models/station_to_station.py
wmataio/rail/models/track_circuit.py
pywmataio-0.0.8.dist-info/LICENSE
pywmataio-0.0.8.dist-info/METADATA
pywmataio-0.0.8.dist-info/WHEEL
pywmataio-0.0.8.dist-info/top_level.txt
pywmataio-0.0.8.dist-info/RECORD
