Metadata-Version: 2.1
Name: pywmataio
Version: 0.0.8
Summary: A simple async interface to the WMATA (Washington, DC Public Transit) API
Home-page: https://github.com/raman325/pywmataio
Author: Raman
Author-email: 7243222+raman325@users.noreply.github.com
Classifier: Intended Audience :: Developers
Classifier: License :: OSI Approved :: MIT License
Classifier: Natural Language :: English
Classifier: Operating System :: OS Independent
Classifier: Programming Language :: Python :: 3
Classifier: Programming Language :: Python :: 3.10
Classifier: Programming Language :: Python :: 3.11
Requires-Python: >=3.10
License-File: LICENSE
Requires-Dist: aiohttp
